{"trial_id": "04", "hyperparameters": {"space": [{"class_name": "Int", "config": {"name": "num_layers", "default": null, "conditions": [], "min_value": 1, "max_value": 3, "step": 1, "sampling": "linear"}}, {"class_name": "Int", "config": {"name": "units_0", "default": null, "conditions": [], "min_value": 16, "max_value": 64, "step": 16, "sampling": "linear"}}, {"class_name": "Choice", "config": {"name": "activation_0", "default": "relu", "conditions": [], "values": ["relu", "tanh"], "ordered": false}}, {"class_name": "Float", "config": {"name": "dropout_0", "default": 0.1, "conditions": [], "min_value": 0.1, "max_value": 0.4, "step": 0.1, "sampling": "linear"}}, {"class_name": "Choice", "config": {"name": "optimizer", "default": "adam", "conditions": [], "values": ["adam", "sgd", "rmsprop"], "ordered": false}}, {"class_name": "Int", "config": {"name": "units_1", "default": null, "conditions": [], "min_value": 16, "max_value": 64, "step": 16, "sampling": "linear"}}, {"class_name": "Choice", "config": {"name": "activation_1", "default": "relu", "conditions": [], "values": ["relu", "tanh"], "ordered": false}}, {"class_name": "Float", "config": {"name": "dropout_1", "default": 0.1, "conditions": [], "min_value": 0.1, "max_value": 0.4, "step": 0.1, "sampling": "linear"}}, {"class_name": "Int", "config": {"name": "units_2", "default": null, "conditions": [], "min_value": 16, "max_value": 64, "step": 16, "sampling": "linear"}}, {"class_name": "Choice", "config": {"name": "activation_2", "default": "relu", "conditions": [], "values": ["relu", "tanh"], "ordered": false}}, {"class_name": "Float", "config": {"name": "dropout_2", "default": 0.1, "conditions": [], "min_value": 0.1, "max_value": 0.4, "step": 0.1, "sampling": "linear"}}], "values": {"num_layers": 1, "units_0": 32, "activation_0": "tanh", "dropout_0": 0.1, "optimizer": "sgd", "units_1": 64, "activation_1": "tanh", "dropout_1": 0.30000000000000004, "units_2": 32, "activation_2": "relu", "dropout_2": 0.2}}, "metrics": {"metrics": {"accuracy": {"direction": "max", "observations": [{"value": [0.7894034385681152], "step": 46}]}, "loss": {"direction": "min", "observations": [{"value": [0.4509119391441345], "step": 46}]}, "val_accuracy": {"direction": "max", "observations": [{"value": [0.7894999980926514], "step": 46}]}, "val_loss": {"direction": "min", "observations": [{"value": [0.4422132968902588], "step": 46}]}}}, "score": 0.7894999980926514, "best_step": 46, "status": "COMPLETED", "message": null}